testcat/__init__.py
testcat/fixtures.py
testcat/fixtures_test.py
toolcat/__init__.py
toolcat/command.py
toolcat/database.py
toolcat/database_test.py
toolcat/files.py
toolcat/project.py
toolcat/projects_test.py
toolcat-0.1.0.dist-info/LICENSE
toolcat-0.1.0.dist-info/METADATA
toolcat-0.1.0.dist-info/WHEEL
toolcat-0.1.0.dist-info/RECORD
